{
  "02101": { "zone": "7a", "lat": 42.36,  "lon": -71.06  },
  "02134": { "zone": "7a", "lat": 42.35,  "lon": -71.13  },
  "03101": { "zone": "6a", "lat": 42.99,  "lon": -71.46  },
  "04101": { "zone": "6a", "lat": 43.66,  "lon": -70.26  },
  "06101": { "zone": "6b", "lat": 41.76,  "lon": -72.68  },
  "07102": { "zone": "7a", "lat": 40.74,  "lon": -74.17  },
  "10001": { "zone": "7b", "lat": 40.75,  "lon": -74.00  },
  "11201": { "zone": "7b", "lat": 40.69,  "lon": -73.99  },
  "13201": { "zone": "5b", "lat": 43.05,  "lon": -76.15  },
  "14201": { "zone": "6a", "lat": 42.89,  "lon": -78.86  },
  "19103": { "zone": "7a", "lat": 39.95,  "lon": -75.17  },
  "20001": { "zone": "7b", "lat": 38.91,  "lon": -77.02  },
  "20002": { "zone": "7b", "lat": 38.90,  "lon": -76.99  },
  "20003": { "zone": "7b", "lat": 38.88,  "lon": -76.99  },
  "20004": { "zone": "7b", "lat": 38.90,  "lon": -77.03  },
  "20005": { "zone": "7b", "lat": 38.90,  "lon": -77.03  },
  "20006": { "zone": "7b", "lat": 38.90,  "lon": -77.04  },
  "20007": { "zone": "7b", "lat": 38.91,  "lon": -77.07  },
  "20008": { "zone": "7b", "lat": 38.94,  "lon": -77.06  },
  "20009": { "zone": "7b", "lat": 38.92,  "lon": -77.04  },
  "20010": { "zone": "7b", "lat": 38.93,  "lon": -77.03  },
  "20011": { "zone": "7b", "lat": 38.95,  "lon": -77.02  },
  "20012": { "zone": "7b", "lat": 38.98,  "lon": -77.03  },
  "20015": { "zone": "7b", "lat": 38.97,  "lon": -77.07  },
  "20016": { "zone": "7b", "lat": 38.94,  "lon": -77.09  },
  "20017": { "zone": "7b", "lat": 38.93,  "lon": -76.99  },
  "20018": { "zone": "7b", "lat": 38.92,  "lon": -76.97  },
  "20019": { "zone": "7b", "lat": 38.89,  "lon": -76.94  },
  "20020": { "zone": "7b", "lat": 38.86,  "lon": -76.98  },
  "20024": { "zone": "7b", "lat": 38.88,  "lon": -77.02  },
  "20032": { "zone": "7b", "lat": 38.84,  "lon": -77.00  },
  "20036": { "zone": "7b", "lat": 38.91,  "lon": -77.04  },
  "20037": { "zone": "7b", "lat": 38.90,  "lon": -77.05  },
  "21201": { "zone": "7a", "lat": 39.29,  "lon": -76.62  },
  "23219": { "zone": "7b", "lat": 37.54,  "lon": -77.44  },
  "27601": { "zone": "7b", "lat": 35.78,  "lon": -78.64  },
  "28202": { "zone": "8a", "lat": 35.23,  "lon": -80.84  },
  "29201": { "zone": "8a", "lat": 34.00,  "lon": -81.03  },
  "30301": { "zone": "8b", "lat": 33.75,  "lon": -84.39  },
  "32202": { "zone": "9a", "lat": 30.33,  "lon": -81.66  },
  "33101": { "zone": "11a","lat": 25.77,  "lon": -80.19  },
  "33602": { "zone": "9b", "lat": 27.95,  "lon": -82.46  },
  "35203": { "zone": "8a", "lat": 33.52,  "lon": -86.80  },
  "37201": { "zone": "7b", "lat": 36.17,  "lon": -86.78  },
  "38103": { "zone": "8a", "lat": 35.15,  "lon": -90.05  },
  "40202": { "zone": "6b", "lat": 38.25,  "lon": -85.76  },
  "43215": { "zone": "6b", "lat": 39.96,  "lon": -83.00  },
  "44114": { "zone": "6a", "lat": 41.50,  "lon": -81.69  },
  "45202": { "zone": "7a", "lat": 39.10,  "lon": -84.51  },
  "46204": { "zone": "6a", "lat": 39.77,  "lon": -86.16  },
  "48226": { "zone": "6b", "lat": 42.33,  "lon": -83.05  },
  "53202": { "zone": "6a", "lat": 43.04,  "lon": -87.91  },
  "55402": { "zone": "5a", "lat": 44.98,  "lon": -93.27  },
  "60601": { "zone": "6b", "lat": 41.88,  "lon": -87.63  },
  "63101": { "zone": "7a", "lat": 38.63,  "lon": -90.20  },
  "64106": { "zone": "6b", "lat": 39.10,  "lon": -94.58  },
  "70112": { "zone": "9a", "lat": 29.95,  "lon": -90.07  },
  "73102": { "zone": "7b", "lat": 35.47,  "lon": -97.52  },
  "75201": { "zone": "8a", "lat": 32.78,  "lon": -96.80  },
  "77002": { "zone": "9b", "lat": 29.75,  "lon": -95.37  },
  "78201": { "zone": "8b", "lat": 29.42,  "lon": -98.49  },
  "78701": { "zone": "8b", "lat": 30.27,  "lon": -97.74  },
  "80202": { "zone": "6b", "lat": 39.75,  "lon": -104.99 },
  "84101": { "zone": "7a", "lat": 40.76,  "lon": -111.89 },
  "85003": { "zone": "10b","lat": 33.45,  "lon": -112.07 },
  "85701": { "zone": "9b", "lat": 32.22,  "lon": -110.97 },
  "89101": { "zone": "10a","lat": 36.17,  "lon": -115.14 },
  "90012": { "zone": "11a","lat": 34.05,  "lon": -118.24 },
  "92101": { "zone": "11a","lat": 32.72,  "lon": -117.16 },
  "94102": { "zone": "10b","lat": 37.78,  "lon": -122.42 },
  "95814": { "zone": "9b", "lat": 38.58,  "lon": -121.49 },
  "97201": { "zone": "9a", "lat": 45.52,  "lon": -122.68 },
  "98101": { "zone": "9b", "lat": 47.60,  "lon": -122.33 },
  "99501": { "zone": "4a", "lat": 61.22,  "lon": -149.90 },
  "96813": { "zone": "13a","lat": 21.31,  "lon": -157.86 }
}
